{
	"configurations" : 
	[
		{
			"directories" : 
			[
				{
					"build" : ".",
					"hasInstallRule" : true,
					"jsonFile" : "directory-.-c6f2ba9a0d430729d4e1.json",
					"minimumCMakeVersion" : 
					{
						"string" : "3.12"
					},
					"projectIndex" : 0,
					"source" : ".",
					"targetIndexes" : 
					[
						0,
						1,
						2
					]
				}
			],
			"name" : "",
			"projects" : 
			[
				{
					"directoryIndexes" : 
					[
						0
					],
					"name" : "ballistic_solver",
					"targetIndexes" : 
					[
						0,
						1,
						2
					]
				}
			],
			"targets" : 
			[
				{
					"directoryIndex" : 0,
					"id" : "ballistic_solver_uninstall::@6890427a1f51a3e7e1df",
					"jsonFile" : "target-ballistic_solver_uninstall-a3c6bdd5e56e2b087b3e.json",
					"name" : "ballistic_solver_uninstall",
					"projectIndex" : 0
				},
				{
					"directoryIndex" : 0,
					"id" : "solver_node::@6890427a1f51a3e7e1df",
					"jsonFile" : "target-solver_node-de56bdba850d1de504b9.json",
					"name" : "solver_node",
					"projectIndex" : 0
				},
				{
					"directoryIndex" : 0,
					"id" : "uninstall::@6890427a1f51a3e7e1df",
					"jsonFile" : "target-uninstall-8492c8f256cda14715af.json",
					"name" : "uninstall",
					"projectIndex" : 0
				}
			]
		}
	],
	"kind" : "codemodel",
	"paths" : 
	{
		"build" : "/home/zph/task/build/ballistic_solver",
		"source" : "/home/zph/task/vision/dist/src/ballistic_solver"
	},
	"version" : 
	{
		"major" : 2,
		"minor" : 3
	}
}
